tangible-0.2.2.dist-info/RECORD
tangible-0.2.2.dist-info/DESCRIPTION.rst
tangible-0.2.2.dist-info/metadata.json
tangible-0.2.2.dist-info/METADATA
tangible-0.2.2.dist-info/top_level.txt
tangible-0.2.2.dist-info/WHEEL
tangible/__init__.py
tangible/utils.py
tangible/ast.py
tangible/scales.py
tangible/backends/__init__.py
tangible/backends/openscad.py
tangible/shapes/vertical.py
tangible/shapes/__init__.py
tangible/shapes/base.py
tangible/shapes/mixins.py
tangible/shapes/pie.py
tangible/shapes/bars.py
