Metadata-Version: 2.0
Name: tangible
Version: 0.2.2
Summary: A Python library to convert data into tangible 3D models.
Home-page: https://github.com/dbrgn/tangible
Author: Danilo Bargen
Author-email: mail@dbrgn.ch
License: LGPLv3
Keywords: tangible visualization 3d printing
Platform: any
Classifier: Development Status :: 4 - Beta
Classifier: License :: OSI Approved :: GNU Lesser General Public License v3 or later (LGPLv3+)
Classifier: Operating System :: OS Independent
Classifier: Programming Language :: Python
Classifier: Programming Language :: Python :: 2
Classifier: Programming Language :: Python :: 2.6
Classifier: Programming Language :: Python :: 2.7
Classifier: Programming Language :: Python :: 2 :: Only
Classifier: Topic :: Artistic Software
Classifier: Topic :: Multimedia :: Graphics :: 3D Modeling
Classifier: Topic :: Scientific/Engineering :: Visualization
Classifier: Topic :: Software Development :: Libraries :: Python Modules
